LICENSE
sequifier/config/infer_config.py
sequifier/config/preprocess_config.py
sequifier/config/train_config.py
sequifier/helpers.py
sequifier/infer.py
sequifier/preprocess.py
sequifier/sequifier.py
sequifier/train.py
sequifier-3.0.0.dist-info/LICENSE
sequifier-3.0.0.dist-info/METADATA
sequifier-3.0.0.dist-info/WHEEL
sequifier-3.0.0.dist-info/entry_points.txt
sequifier-3.0.0.dist-info/RECORD
