Metadata-Version: 2.1
Name: sequifier
Version: 3.0.0
Summary: Train a transformer model with the command line
Home-page: https://github.com/0xideas/sequifier
License: BSD 3-Clause
Keywords: transformer,sequence classification,machine learning,sequence,sequence modelling,nlp,language,language modelling,torch,pytorch
Author: Leon Luithlen
Author-email: leontimnaluithlen@gmail.com
Requires-Python: >=3.9,<4.0
Classifier: License :: Other/Proprietary License
Classifier: Programming Language :: Python :: 3
Classifier: Programming Language :: Python :: 3.9
Classifier: Programming Language :: Python :: 3.10
Classifier: Programming Language :: Python :: 3.11
Classifier: Programming Language :: Python :: 3.12
Requires-Dist: csvkit (>=1.0,<2.0)
Requires-Dist: fastparquet (>=2024.2.0,<2025.0.0)
Requires-Dist: numpy (>=1.23,<2.0)
Requires-Dist: onnx (>=1.15.0,<2.0.0)
Requires-Dist: onnxruntime (>=1.17,<2.0)
Requires-Dist: pandas (>=2.0,<3.0)
Requires-Dist: poetry (>=1.3,<2.0)
Requires-Dist: pyarrow (>=15.0,<16.0)
Requires-Dist: pydantic (>=1.10,<2.0)
Requires-Dist: pytest (>=7.2,<8.0)
Requires-Dist: pyyaml (>=6.0,<7.0)
Requires-Dist: torch (>=2.0,<3.0)
Project-URL: Repository, https://github.com/0xideas/sequifier
